touchfs/__init__.py
touchfs/__main__.py
touchfs/cli/__init__.py
touchfs/cli/context_command.py
touchfs/cli/generate_command.py
touchfs/cli/interactive.py
touchfs/cli/mount_command.py
touchfs/cli/touch_command.py
touchfs/cli/touchfs_cli.py
touchfs/cli/umount_command.py
touchfs/cli/touch/__init__.py
touchfs/cli/touch/cli.py
touchfs/cli/touch/path_utils.py
touchfs/cli/touch/ui.py
touchfs/config/__init__.py
touchfs/config/context.py
touchfs/config/features.py
touchfs/config/filesystem.py
touchfs/config/logger.py
touchfs/config/model.py
touchfs/config/prompts.py
touchfs/config/settings.py
touchfs/config/templates.py
touchfs/config/xattrs.py
touchfs/content/__init__.py
touchfs/content/generator.py
touchfs/content/plugins/__init__.py
touchfs/content/plugins/base.py
touchfs/content/plugins/cache_control.py
touchfs/content/plugins/default.py
touchfs/content/plugins/log_symlink.py
touchfs/content/plugins/model.py
touchfs/content/plugins/multiproc.py
touchfs/content/plugins/proc.py
touchfs/content/plugins/prompt.py
touchfs/content/plugins/readme.py
touchfs/content/plugins/registry.py
touchfs/content/plugins/touch_detector.py
touchfs/content/plugins/tree.py
touchfs/content/plugins/image/__init__.py
touchfs/content/plugins/image/cache.py
touchfs/content/plugins/image/constants.py
touchfs/content/plugins/image/generator.py
touchfs/content/plugins/image/prompt.py
touchfs/content/plugins/image/types.py
touchfs/core/__init__.py
touchfs/core/cache.py
touchfs/core/cache_stats.py
touchfs/core/jsonfs.py
touchfs/core/context/__init__.py
touchfs/core/context/context.py
touchfs/core/memory/__init__.py
touchfs/core/memory/base.py
touchfs/core/memory/dir_ops.py
touchfs/core/memory/file_ops.py
touchfs/core/memory/link_ops.py
touchfs/core/memory/memory.py
touchfs/core/memory/meta_ops.py
touchfs/core/memory/touch_ops.py
touchfs/core/memory/xattr_ops.py
touchfs/models/__init__.py
touchfs/models/cache_keys.py
touchfs/models/filename_suggestions.py
touchfs/models/filesystem.py
touchfs-0.2.0.dist-info/METADATA
touchfs-0.2.0.dist-info/WHEEL
touchfs-0.2.0.dist-info/entry_points.txt
touchfs-0.2.0.dist-info/top_level.txt
touchfs-0.2.0.dist-info/RECORD
