Metadata-Version: 2.2
Name: touchfs
Version: 0.2.0
Summary: A context-aware filesystem that generates content on demand using LLMs
Home-page: https://github.com/kristerhedfors/touchfs
Author: Krister Hedfors
Author-email: krister.hedfors@gmail.com
Classifier: Development Status :: 4 - Beta
Classifier: Intended Audience :: Developers
Classifier: License :: OSI Approved :: MIT License
Classifier: Operating System :: POSIX :: Linux
Classifier: Programming Language :: Python :: 3
Classifier: Programming Language :: Python :: 3.8
Classifier: Programming Language :: Python :: 3.9
Classifier: Programming Language :: Python :: 3.10
Classifier: Topic :: System :: Filesystems
Requires-Python: >=3.8
Requires-Dist: fusepy
Requires-Dist: pytest>=7.0.0
Requires-Dist: openai>=1.0.0
Requires-Dist: pydantic>=2.0.0
Requires-Dist: python-dotenv>=0.19.0
Requires-Dist: PyYAML>=6.0.0
Requires-Dist: tiktoken>=0.5.0
Requires-Dist: psutil>=5.9.0
Dynamic: author
Dynamic: author-email
Dynamic: classifier
Dynamic: description
Dynamic: description-content-type
Dynamic: home-page
Dynamic: requires-dist
Dynamic: requires-python
Dynamic: summary
